pyggwave.cpython-310-x86_64-linux-gnu.so
pyggwave-0.4.2.7.dist-info/METADATA
pyggwave-0.4.2.7.dist-info/WHEEL
pyggwave-0.4.2.7.dist-info/top_level.txt
pyggwave-0.4.2.7.dist-info/RECORD
