Metadata-Version: 2.4
Name: pyggwave
Version: 0.4.2.7
Summary: Tiny data-over-sound library with better documentation and more functions.
Home-page: https://github.com/tpyauheni/pyggwave
Author: Yauheni
Author-email: eduartpastado@gmail.com
License: MIT
Keywords: data-over-sound fsk ecc serverless pairing qrcode ultrasound
Dynamic: author
Dynamic: author-email
Dynamic: description
Dynamic: description-content-type
Dynamic: home-page
Dynamic: keywords
Dynamic: license
Dynamic: summary
